Workbook

Sheet Inicio
A1: VI CONCEPMI LIMA 2026 · CONCURSO NACIONAL DE PROYECTOS
A2: ENTREGABLE 4 · PLAN FINANCIERO Y COSTOS | Plantilla simplificada según la rúbrica oficial
A4: ANTES DE EMPEZAR
A5: Completen solo las celdas amarillas. Las celdas lilas contienen fórmulas. No hace falta tener ventas ni un MVP terminado: registren la etapa real y sustenten los supuestos financieros.
A7: DATOS DEL PROYECTO
A8: Delegación | E8: Proyecto
A9: Líder de equipo | E9: Correo del líder
A10: Etapa actual | C10: Ventas actuales | E10: Tipo de proyecto | G10: Selecciona las opciones
A12: CÓMO COMPLETAR EL ENTREGABLE
A13: 1 · COSTOS (3 pts) | C13: Lista de partidas de costo y marca cada una como CAPEX (inversión inicial) u OPEX (operación/tecnología).
A14: 2 · RESERVAS (2 pts) | C14: Copia 3–5 riesgos principales y su VME desde el Entregable 3. Las reservas 10 % y 5 % se calculan solas.
A15: 3 · UNIT ECONOMICS (3 pts) | C15: Define unidad, ingreso/precio, costo variable, margen y punto de equilibrio. Usa estimaciones justificadas si aún no vendes.
A17: ADÁPTALA A TU CASO
A18: CON VENTAS: usa precios, costos por unidad y ventas mensuales observadas o promedios reales.
A19: SIN VENTAS: usa precio/ingreso y volumen mensual estimados, sustentados en el Entregable 1 (entrevistas, encuestas, competencia, intención de compra u otra evidencia). No los presentes como ventas reales.
A20: IDEA, PROTOTIPO O MVP: elige tu etapa y estima los costos que realmente necesitas para llegar al siguiente hito. Para proyectos sociales/no comerciales, define una unidad de servicio o beneficiario e indica qué fuente financiaría cada unidad.
A22: RÚBRICA OFICIAL · 8 PUNTOS
A23: Criterio | D23: Qué debe mostrar | G23: Pts | H23: Hoja
A24: Estructura de costos | D24: CAPEX + OPEX en una lista ordenada, con cantidades, costos y sustento. | G24: 3 | H24: Costos
A25: Sustento de reservas | D25: Contingencia 10 % para riesgos conocidos y gestión 5 % para imprevistos, con justificación. | G25: 2 | H25: Reservas
A26: Unit Economics | D26: Ingreso/precio por unidad, costo unitario, margen y punto de equilibrio. | G26: 3 | H26: UnitEconomics
A27: TOTAL | G27: 8
A29: Fecha límite indicada en las bases: sábado 21 de noviembre de 2026. Completa las hojas en este orden: Costos → Reservas → UnitEconomics → revisa Resumen.

Sheet Costos
A1: ENTREGABLE 4 · ESTRUCTURA DE COSTOS
A2: Subcriterio 1 · 3 puntos | Completa solo las partidas que apliquen al proyecto.
A4: RÚBRICA: desglose de costos de desarrollo (CAPEX) y operativos/tecnológicos (OPEX) mediante una EDC sencilla.
A5: CAPEX = inversión inicial para desarrollar/implementar. OPEX = costos operativos/tecnológicos del horizonte indicado. Los costos variables por unidad van en UnitEconomics, no aquí.
A7: Horizonte OPEX (meses) | B7: 12 | C7: Todos los OPEX de la tabla deben cubrir este periodo (por ejemplo, 12 meses).
A8: En cada fila indica concepto, tipo, cantidad, costo unitario y una fuente o supuesto breve (cotización, precio publicado o estimación).
A9: N.º | B9: Partida / concepto de costo | C9: Tipo | D9: Cantidad | E9: Costo unitario (S/) | F9: Costo total (S/) | G9: Sustento / fuente breve
A10: 1 | F10: =IF(B10="","",IF(D10="","",IF(E10="","",D10*E10)))
A11: 2 | F11: =IF(B11="","",IF(D11="","",IF(E11="","",D11*E11)))
A12: 3 | F12: =IF(B12="","",IF(D12="","",IF(E12="","",D12*E12)))
A13: 4 | F13: =IF(B13="","",IF(D13="","",IF(E13="","",D13*E13)))
A14: 5 | F14: =IF(B14="","",IF(D14="","",IF(E14="","",D14*E14)))
A15: 6 | F15: =IF(B15="","",IF(D15="","",IF(E15="","",D15*E15)))
A16: 7 | F16: =IF(B16="","",IF(D16="","",IF(E16="","",D16*E16)))
A17: 8 | F17: =IF(B17="","",IF(D17="","",IF(E17="","",D17*E17)))
A18: 9 | F18: =IF(B18="","",IF(D18="","",IF(E18="","",D18*E18)))
A19: 10 | F19: =IF(B19="","",IF(D19="","",IF(E19="","",D19*E19)))
A20: 11 | F20: =IF(B20="","",IF(D20="","",IF(E20="","",D20*E20)))
A21: 12 | F21: =IF(B21="","",IF(D21="","",IF(E21="","",D21*E21)))
... A23: 14 | F23: =IF(B23="","",IF(D23="","",IF(E23="","",D23*E23)))
A25: TOTAL CAPEX · inversión inicial | F25: =SUMIF(C10:C23,"CAPEX",F10:F23) -> 0 | G25: Sumatoria automática
A26: TOTAL OPEX · costos del horizonte seleccionado | F26: =SUMIF(C10:C23,"OPEX",F10:F23) -> 0 | G26: Costos operativos durante el horizonte
A27: COSTOS DIRECTOS TOTALES | F27: =SUM(F10:F23) -> 0 | G27: CAPEX + OPEX
A28: OPEX FIJO MENSUAL · OPEX ÷ horizonte | F28: =IF(B7>0,F26/B7,0) -> 0 | G28: Se conecta con el punto de equilibrio
A29: Verificación de clasificación | F29: =IF(F27=0,"Añade/complete partidas",IF(ABS(F27-F25-F26)<0.01,"Suma CAPEX/OPEX consistente","Revisar CAPEX/OPEX")) -> Añade/complete partidas | G29: Todos los costos deben tener tipo
A31: Recuerda: las cantidades y los precios pueden ser estimados, pero deben ser razonables y llevar sustento. No dupliques aquí los costos variables por unidad.

Sheet Reservas
A1: ENTREGABLE 4 · RESERVAS DEL PROYECTO
A2: Subcriterio 2 · 2 puntos | Contingencia: 10 % para riesgos conocidos · Gestión: 5 % para imprevistos.
A4: RÚBRICA: justifica las reservas del 10 % y 5 % y demuestra que la contingencia es razonable frente a los riesgos identificados.
A5: Los porcentajes se calculan automáticamente. Copia solo los 3–5 riesgos más importantes del Entregable 3 e indica el VME que ya calcularon allí.
A6: CÁLCULO AUTOMÁTICO
A7: Costos directos (CAPEX + OPEX) | C7: =Costos!F27 -> 0 | D7: Enlazado desde Costos
A8: % reserva de contingencia | C8: =0.1 -> 0.1 | D8: Fijo según las bases: 10 %
A9: Reserva de contingencia | C9: =C7*C8 -> 0 | D9: Costos directos × 10 %
A10: Base para reserva de gestión | C10: =C7+C9 -> 0 | D10: Costos directos + contingencia
A11: % reserva de gestión | C11: =0.05 -> 0.05 | D11: Fijo según las bases: 5 %
A12: Reserva de gestión | C12: =C10*C11 -> 0 | D12: Base × 5 %
A13: PRESUPUESTO TOTAL ESTIMADO | C13: =C10+C12 -> 0 | D13: Base + reserva de gestión
A15: RIESGOS CONOCIDOS · COPIAR DEL ENTREGABLE 3
A16: Registra los riesgos de mayor exposición; no necesitas repetir el análisis completo. Usa el VME (probabilidad × impacto) calculado en el Entregable 3.
A17: ID riesgo | B17: Riesgo principal (breve) | C17: VME (S/) | D17: Referencia en Entregable 3
A18: R01
A19: R02
A20: R03
A21: R04
A22: R05
A23: Exposición total (suma de VME) | C23: =SUM(C18:C22) -> 0
A24: Cobertura de contingencia (reserva − exposición) | C24: =C9-C23 -> 0
A25: Verificación | C25: =IF(C23=0,"Añade VME de E3",IF(C24>=0,"Reserva cubre exposición","Exposición supera reserva")) -> Añade VME de E3
A27: JUSTIFICACIÓN BREVE (1–3 líneas por reserva)
A28: ¿Por qué el 10 % es razonable para los riesgos conocidos?
A29: ¿Qué imprevistos cubriría el 5 % y quién autoriza usarlo?

Sheet UnitEconomics
A1: ENTREGABLE 4 · UNIT ECONOMICS Y MODELO DE INGRESOS
A2: Subcriterio 3 · 3 puntos | Calcula costo unitario, margen y punto de equilibrio con datos reales o supuestos claros.
A4: RÚBRICA: ingreso/precio por unidad, costos variables unitarios, margen de ganancia y punto de equilibrio.
A6: A. MODELO DEL PROYECTO
A7: Etapa actual | B7: =IF(Inicio!B10="","",Inicio!B10) | C7: Elegida en Inicio; puede ser idea, prototipo o MVP.
A8: Ventas actuales | B8: =IF(Inicio!D10="","",Inicio!D10) | C8: Si no hay ventas, usa estimaciones y decláralas como tales.
A9: Tipo de proyecto | B9: =IF(Inicio!F10="","",Inicio!F10) | C9: Si es social/no comercial, define una unidad de servicio o beneficiario.
A10: Unidad de análisis
A11: Quién paga/financia y por qué
A12: Precio o ingreso/financiamiento por unidad (S/)
A13: Con ventas: precio promedio real. Sin ventas: precio/ingreso esperado con sustento del Entregable 1. No registres ventas ficticias.
A14: B. COSTOS VARIABLES POR UNIDAD
A15: Costo variable por unidad | B15: Costo unitario (S/) | C15: Fuente / supuesto
A21: Costo variable total por unidad | B21: =SUM(B16:B20) -> 0
A22: Margen por unidad = ingreso − costo variable | B22: =IF(B12="","",IF(B21="","",B12-B21))
A23: Margen sobre ingreso (%) | B23: =IF(B12="","",IF(B22="","",IF(B12>0,B22/B12,0)))
A24: C. PUNTO DE EQUILIBRIO Y ESCENARIO MENSUAL
A25: OPEX fijo mensual (S/) | B25: =IF(Costos!F27=0,"",Costos!F28) | C25: Enlazado desde Costos.
A26: Unidades/servicios por mes (real o estimado) | C26: Con ventas: promedio observado. Sin ventas: escenario base razonable.
A27: Ingreso/financiamiento mensual estimado (S/) | B27: =IF(B12="","",IF(B26="","",B12*B26)) | C27: Ingreso por unidad × unidades/servicios del mes.
A28: Resultado mensual estimado (S/) | B28: =IF(B22="","",IF(B26="","",B22*B26-B25)) | C28: Margen unitario × unidades − OPEX fijo mensual.
A29: Punto de equilibrio (unidades/mes) | B29: =IF(B22="","Completar ingreso/costos",IF(B22<=0,"Revisar margen",ROUNDUP(B25/B22,0))) -> Completar ingreso/costos | C29: Unidades para cubrir el OPEX fijo mensual.
A30: Punto de equilibrio (ingreso mensual, S/) | B30: =IF(ISNUMBER(B29),B29*B12,"—") -> — | C30: Unidades de equilibrio × ingreso por unidad.
A31: Presupuesto total estimado (S/) | B31: =IF(Reservas!C7=0,"",Reservas!C13) | C31: Enlazado desde Reservas.
A32: Recuperación de inversión (meses) | B32: =IF(B28>0,B31/B28,"No estimable en este escenario") -> #VALUE! | C32: Solo estimable si el resultado mensual es positivo.
A34: Sustento breve de los supuestos (precio/ingreso, volumen y costo variable)

Sheet Resumen
A1: ENTREGABLE 4 · RESUMEN FINANCIERO
A2: Revisión final automática · Verifica los supuestos y la cobertura de los criterios de la rúbrica.
A4: INDICADORES PRINCIPALES
A5: Indicador | B5: Resultado | C5: Origen / lectura
A6: CAPEX · inversión inicial | B6: =IF(Costos!F27=0,"",Costos!F25) | C6: Costos
A7: OPEX · periodo seleccionado | B7: =IF(Costos!F27=0,"",Costos!F26) | C7: Costos
A8: Costos directos totales | B8: =IF(Costos!F27=0,"",Costos!F27) | C8: CAPEX + OPEX
A9: Reserva de contingencia 10 % | B9: =IF(Costos!F27=0,"",Reservas!C9) | C9: Riesgos conocidos
A10: Reserva de gestión 5 % | B10: =IF(Costos!F27=0,"",Reservas!C12) | C10: Imprevistos
A11: Presupuesto total estimado | B11: =IF(Costos!F27=0,"",Reservas!C13) | C11: Costos + reservas
A12: Ingreso/precio por unidad | B12: =IF(UnitEconomics!B12="","",UnitEconomics!B12) | C12: Real o estimado
A13: Costo variable por unidad | B13: =IF(UnitEconomics!B21="","",UnitEconomics!B21) -> 0 | C13: Unit economics
A14: Margen por unidad | B14: =IF(UnitEconomics!B22="","",UnitEconomics!B22) | C14: Ingreso − costo variable
A15: Margen sobre ingreso | B15: =IF(UnitEconomics!B23="","",UnitEconomics!B23) | C15: %
A16: Punto de equilibrio (unidades/mes) | B16: =UnitEconomics!B29 -> Completar ingreso/costos | C16: Con margen positivo
A17: Resultado mensual estimado | B17: =UnitEconomics!B28 | C17: Escenario real o base
A18: Recuperación estimada (meses) | B18: =UnitEconomics!B32 -> #VALUE! | C18: Si el resultado es positivo
A19: LISTA DE VERIFICACIÓN ANTES DE ENTREGAR
A20: Comprobación | B20: Estado | C20: Qué revisar
A21: Todos los costos están clasificados | B21: =Costos!F29 -> Añade/complete partidas | C21: Cada partida está marcada CAPEX u OPEX.
A22: La contingencia cubre el VME reportado | B22: =Reservas!C25 -> Añade VME de E3 | C22: Si supera el 10 %, expliquen la brecha.
A23: Ingreso/precio por unidad completado | B23: =IF(UnitEconomics!B12>0,"OK","Completar ingreso/precio unitario") -> Completar ingreso/precio unitario | C23: Si no hay ventas, indicar que es estimado.
A24: Costo variable por unidad registrado | B24: =IF(UnitEconomics!B21>0,"OK","Registrar costo variable o justificar 0") -> Registrar costo variable o justificar 0 | C24: Si no aplica algún costo, registrar 0 o explicar.
A25: Margen y punto de equilibrio revisados | B25: =IF(UnitEconomics!B22>0,"Calculado","Revisar margen o supuesto de ingreso") -> Calculado | C25: El margen debe permitir calcular el equilibrio.
A26: Supuestos financieros explicados | B26: =IF(UnitEconomics!C34="","Añadir sustento","Verificar sustento") -> Añadir sustento | C26: Explica brevemente precio/ingreso, volumen y costos.
A29: Nota: el modelo puede usar datos reales (con ventas) o estimaciones justificadas (sin ventas). No declares proyecciones como resultados reales.
